oxen_pyo3-0.1.3.dist-info/METADATA
oxen_pyo3-0.1.3.dist-info/WHEEL
oxen_pyo3/__init__.py
oxen_pyo3/__init__.pyi
oxen_pyo3/py.typed
oxen_pyo3/oxen_pyo3.cp312-win_amd64.pyd
oxen_pyo3-0.1.3.dist-info/RECORD
