Metadata-Version: 2.4
Name: oxen_pyo3
Version: 0.1.3
Requires-Dist: maturin>=1.8.1
Requires-Dist: patchelf>=0.17.2.1 ; sys_platform == 'linux'
Summary: Add your description here
Requires-Python: >=3.11
